andersan/__init__.py
andersan/tile.py
andersan-0.1.4.dist-info/METADATA
andersan-0.1.4.dist-info/WHEEL
andersan-0.1.4.dist-info/RECORD
