Metadata-Version: 2.1
Name: andersan
Version: 0.1.4
Summary: Developers' library for Andersan
Author: vitroid
Author-email: vitroid@gmail.com
Requires-Python: >=3.10,<4.0
Classifier: Programming Language :: Python :: 3
Classifier: Programming Language :: Python :: 3.10
Classifier: Programming Language :: Python :: 3.11
Classifier: Programming Language :: Python :: 3.12
Requires-Dist: deprecation (>=2.1.0,<3.0.0)
Requires-Dist: numpy (<2.0)
Requires-Dist: scipy (>=1.14.1,<2.0.0)
